bug_buddy/__init__.py
bug_buddy/_config.py
bug_buddy/_di_container.py
bug_buddy/bb.py
bug_buddy/integration.py
bug_buddy/issue.py
bug_buddy/listener.py
bug_buddy-1.1.0.dist-info/METADATA
bug_buddy-1.1.0.dist-info/WHEEL
bug_buddy-1.1.0.dist-info/licenses/LICENSE
bug_buddy-1.1.0.dist-info/RECORD
