Metadata-Version: 2.4
Name: bug-buddy
Version: 1.1.0
Summary: Auto cache and track Python exceptions via Python decorators.
License: MIT
License-File: LICENSE
Author: Spencer Seale
Author-email: spencerseale17@gmail.com
Requires-Python: >=3.10,<4.0
Classifier: License :: OSI Approved :: MIT License
Classifier: Programming Language :: Python :: 3
Classifier: Programming Language :: Python :: 3.10
Classifier: Programming Language :: Python :: 3.11
Classifier: Programming Language :: Python :: 3.12
Classifier: Programming Language :: Python :: 3.13
Classifier: Programming Language :: Python :: 3.14
Requires-Dist: attrs (>=23.2.0,<24.0.0)
Requires-Dist: pydantic (>=2.5.3,<3.0.0)
